oarc_utils/decorators/__init__.py
oarc_utils/decorators/asyncio_run.py
oarc_utils/decorators/factory.py
oarc_utils/decorators/handle_error.py
oarc_utils/decorators/singleton.py
oarc_utils/errors/__init__.py
oarc_utils/errors/oarc_crawlers_errors.py
oarc_utils-0.1.1.dist-info/licenses/LICENSE
tests/__init__.py
oarc_utils-0.1.1.dist-info/METADATA
oarc_utils-0.1.1.dist-info/WHEEL
oarc_utils-0.1.1.dist-info/top_level.txt
oarc_utils-0.1.1.dist-info/RECORD
