Metadata-Version: 2.4
Name: oarc-utils
Version: 0.1.1
Summary: A global repository of useful python utility scripts and decorators for Ollama Agent Roll Cage (OARC)
Author: OARC Team
Maintainer-email: OARC Team <NotSetup@gmail.com>
License-Expression: Apache-2.0
Project-URL: homepage, https://github.com/Ollama-Agent-Roll-Cage/oarc-utils
Project-URL: repository, https://github.com/Ollama-Agent-Roll-Cage/oarc-utils
Project-URL: documentation, https://github.com/Ollama-Agent-Roll-Cage/oarc-utils#readme
Project-URL: bugtracker, https://github.com/Ollama-Agent-Roll-Cage/oarc-utils/issues
Keywords: ollama,agent,utilities,decorators,cli,python
Classifier: Development Status :: 4 - Beta
Classifier: Intended Audience :: Developers
Classifier: Programming Language :: Python :: 3
Classifier: Programming Language :: Python :: 3.10
Classifier: Programming Language :: Python :: 3.11
Classifier: Programming Language :: Python :: 3.12
Classifier: Programming Language :: Python :: 3.13
Requires-Python: >=3.10
License-File: LICENSE
Requires-Dist: click>=8.1.8
Provides-Extra: dev
Requires-Dist: black; extra == "dev"
Requires-Dist: isort; extra == "dev"
Requires-Dist: mypy; extra == "dev"
Requires-Dist: pytest; extra == "dev"
Requires-Dist: pytest-cov; extra == "dev"
Requires-Dist: pytest-asyncio; extra == "dev"
Requires-Dist: flake8; extra == "dev"
Requires-Dist: pydocstyle; extra == "dev"
Dynamic: license-file
